week_schedule/__init__.py
week_schedule/schedule.py
week_schedule-2.2.dist-info/LICENSE
week_schedule-2.2.dist-info/METADATA
week_schedule-2.2.dist-info/WHEEL
week_schedule-2.2.dist-info/top_level.txt
week_schedule-2.2.dist-info/zip-safe
week_schedule-2.2.dist-info/RECORD
