Metadata-Version: 2.1
Name: week-schedule
Version: 2.2
Summary: Create schedule images of your weekly classes
Home-page: https://github.com/JacobHilbert/week_schedule
Author: Jacob Hilbert
Author-email: jacob.hilbert.tree@gmail.com
License: LICENSE
Platform: UNKNOWN
Classifier: Programming Language :: Python :: 3
Classifier: License :: OSI Approved :: MIT License
Classifier: Operating System :: OS Independent
License-File: LICENSE
Requires-Dist: numpy
Requires-Dist: matplotlib
